didself/__init__.py
didself/registry.py
didself-2.1.dist-info/LICENSE.txt
didself-2.1.dist-info/METADATA
didself-2.1.dist-info/WHEEL
didself-2.1.dist-info/top_level.txt
didself-2.1.dist-info/RECORD
