Metadata-Version: 2.1
Name: didself
Version: 2.1
Summary: A did:self implementation
Home-page: https://github.com/excid-io/did-self-py
Author: Nikos Fotiou
Author-email: fotiou@aueb.gr
License: MIT
Classifier: Programming Language :: Python :: 3
Classifier: License :: OSI Approved :: MIT License
Classifier: Operating System :: OS Independent
Requires-Python: >=3.6, <4
License-File: LICENSE.txt
Requires-Dist: jwcrypto
